pynq_helloworld/__init__.py
pynq_helloworld/notebooks/edge/resizer.bit.link
pynq_helloworld/notebooks/edge/resizer.hwh.link
pynq_helloworld/notebooks/edge/resizer_pl.ipynb
pynq_helloworld/notebooks/edge/resizer_ps.ipynb
pynq_helloworld/notebooks/edge/images/framework.png
pynq_helloworld/notebooks/edge/images/local2shared.png
pynq_helloworld/notebooks/edge/images/resize_accel.png
pynq_helloworld/notebooks/edge/images/resize_bd.png
pynq_helloworld/notebooks/edge/images/resize_bit.png
pynq_helloworld/notebooks/edge/images/resizenb.png
pynq_helloworld/notebooks/edge/images/sahara.jpg
pynq_helloworld/notebooks/edge/images/sd2dram.png
pynq_helloworld/notebooks/edge/resizer.bit.d/resizer.Pynq-ZU.bit
pynq_helloworld/notebooks/edge/resizer.hwh.d/resizer.Pynq-ZU.hwh
pynq_helloworld/notebooks/pcie/resizer.xclbin.link
pynq_helloworld/notebooks/pcie/resizer_device.ipynb
pynq_helloworld/notebooks/pcie/resizer_host.ipynb
pynq_helloworld/notebooks/pcie/images/framework.png
pynq_helloworld/notebooks/pcie/images/hd2dram.png
pynq_helloworld/notebooks/pcie/images/local2shared.png
pynq_helloworld/notebooks/pcie/images/resize_accel.png
pynq_helloworld/notebooks/pcie/images/resize_bd.png
pynq_helloworld/notebooks/pcie/images/resize_bit.png
pynq_helloworld/notebooks/pcie/images/resizenb.png
pynq_helloworld/notebooks/pcie/images/sahara.jpg
pynq_helloworld-2.7.0.dist-info/LICENSE
pynq_helloworld-2.7.0.dist-info/METADATA
pynq_helloworld-2.7.0.dist-info/WHEEL
pynq_helloworld-2.7.0.dist-info/entry_points.txt
pynq_helloworld-2.7.0.dist-info/top_level.txt
pynq_helloworld-2.7.0.dist-info/RECORD
