Metadata-Version: 2.1
Name: pynq-helloworld
Version: 2.7.0
Summary: PYNQ example design supporting edge and PCIE boards
Home-page: https://github.com/Xilinx/PYNQ-HelloWorld.git
Author: Xilinx PYNQ Development Team
Author-email: pynq_support@xilinx.com
License: BSD 3-Clause License
Platform: UNKNOWN
Requires-Python: >=3.6.0
Requires-Dist: ipython
Requires-Dist: matplotlib
Requires-Dist: pynq
